pe2loaddata/__init__.py
pe2loaddata/__main__.py
pe2loaddata/append_illum_cols.py
pe2loaddata/transformer.py
pe2loaddata/content/__init__.py
pe2loaddata/content/handler.py
pe2loaddata/content/item/__init__.py
pe2loaddata/content/item/entry_handler.py
pe2loaddata/content/item/images_handler.py
pe2loaddata/content/item/item_handler.py
pe2loaddata/content/item/map_handler.py
pe2loaddata/content/item/maps_handler.py
pe2loaddata/content/item/plate_handler.py
pe2loaddata/content/item/plates_handler.py
pe2loaddata/content/item/root_handler.py
pe2loaddata/content/item/well_handler.py
pe2loaddata/content/item/wells_handler.py
pe2loaddata-0.2.0.dist-info/LICENSE
pe2loaddata-0.2.0.dist-info/METADATA
pe2loaddata-0.2.0.dist-info/WHEEL
pe2loaddata-0.2.0.dist-info/entry_points.txt
pe2loaddata-0.2.0.dist-info/top_level.txt
pe2loaddata-0.2.0.dist-info/RECORD
