Metadata-Version: 2.1
Name: pe2loaddata
Version: 0.2.0
Requires-Python: >=3.8
License-File: LICENSE
Requires-Dist: click >=7.1.2
Requires-Dist: PyYAML >=5.3.1
Provides-Extra: test
Requires-Dist: pytest >=5.4.3 ; extra == 'test'
